copier_python_dummy/__init__.py
copier_python_dummy-0.0.1.dist-info/LICENSE
copier_python_dummy-0.0.1.dist-info/WHEEL
copier_python_dummy-0.0.1.dist-info/METADATA
copier_python_dummy-0.0.1.dist-info/RECORD
